django_random_id_model.py
django_random_id_model-0.2.0.dist-info/METADATA
django_random_id_model-0.2.0.dist-info/WHEEL
django_random_id_model-0.2.0.dist-info/top_level.txt
django_random_id_model-0.2.0.dist-info/RECORD
