Metadata-Version: 2.1
Name: django-random-id-model
Version: 0.2.0
Summary: A django model abstract class for creating random int primary keys.
Home-page: https://github.com/samirelanduk/django-random-id-model
Author: Sam Ireland
Author-email: mail@samireland.com
License: MIT
Keywords: django orm primary-key
Platform: UNKNOWN
Classifier: Development Status :: 4 - Beta
Classifier: Intended Audience :: Developers
Classifier: License :: OSI Approved :: MIT License
Classifier: Topic :: Scientific/Engineering :: Chemistry
Classifier: Framework :: Django
Classifier: Programming Language :: Python :: 3
Classifier: Programming Language :: Python :: 3.6
Classifier: Programming Language :: Python :: 3.7
Classifier: Programming Language :: Python :: 3.8
Classifier: Programming Language :: Python :: 3.9
Requires-Python: !=2.*, !=3.0.*, !=3.1.*, !=3.2.*, !=3.3.*, !=3.4.*, !=3.5.*
